sqlmlutils/__init__.py
sqlmlutils/connectioninfo.py
sqlmlutils/sentpyscriptDebugIssue.py
sqlmlutils/sqlbuilder.py
sqlmlutils/sqlpythonexecutor.py
sqlmlutils/sqlqueryexecutor.py
sqlmlutils/packagemanagement/__init__.py
sqlmlutils/packagemanagement/dependencyresolver.py
sqlmlutils/packagemanagement/download_script.py
sqlmlutils/packagemanagement/messages.py
sqlmlutils/packagemanagement/packagesqlbuilder.py
sqlmlutils/packagemanagement/pipdownloader.py
sqlmlutils/packagemanagement/pkgutils.py
sqlmlutils/packagemanagement/scope.py
sqlmlutils/packagemanagement/servermethods.py
sqlmlutils/packagemanagement/sqlpackagemanager.py
sqlmlutils-1.2.0.dist-info/LICENSE.txt
sqlmlutils-1.2.0.dist-info/METADATA
sqlmlutils-1.2.0.dist-info/WHEEL
sqlmlutils-1.2.0.dist-info/top_level.txt
sqlmlutils-1.2.0.dist-info/RECORD
